constellationPy/__init__.py
constellationPy/client.py
constellationPy/const.py
constellationPy/serveur.py
constellationPy/sync.py
constellationPy/utils.py
constellationpy-1.2.0.dist-info/METADATA
constellationpy-1.2.0.dist-info/WHEEL
constellationpy-1.2.0.dist-info/entry_points.txt
constellationpy-1.2.0.dist-info/licenses/LICENSE
constellationpy-1.2.0.dist-info/RECORD
