Metadata-Version: 2.1
Name: constellationPy
Version: 1.2.0
Summary: Client Python pour le réseau Constellation.
Author-Email: Julien Jean Malard-Adam <julien.malard@mail.mcgill.ca>
License: AGPL-3.0
Requires-Python: <4.0,>=3.10
Requires-Dist: trio-websocket<1.0.0,>=0.11.0
Requires-Dist: pandas<3.0.0,>=2.0.3
Requires-Dist: trio<1.0.0,>=0.23.1
Requires-Dist: semantic-version<3.0.0,>=2.8.5
Requires-Dist: click<9.0.0,>=8.0.3
Requires-Dist: click-default-group<2.0.0,>=1.2.2
Requires-Dist: urllib3<3.0.0,>=2.0.4
Requires-Dist: appdirs<2.0.0,>=1.4.4
Requires-Dist: requests>=2.32.3
Requires-Dist: numpy>=1.26.4
